ziu/__init__.py
ziu/editfilter.py
ziu/listview.py
ziu/main.py
ziu/qt.py
ziu-0.1.0.data/data/LICENSE
ziu-0.1.0.data/data/README.md
ziu-0.1.0.dist-info/METADATA
ziu-0.1.0.dist-info/RECORD
ziu-0.1.0.dist-info/WHEEL
ziu-0.1.0.dist-info/entry_points.txt
ziu-0.1.0.dist-info/top_level.txt
