Metadata-Version: 2.1
Name: ziu
Version: 0.1.0
Summary: ziu file manager
Home-page: https://github.com/krisfris/ziu
Author: Kris
Author-email: 31852063+krisfris@users.noreply.github.com
License: MIT
Platform: UNKNOWN
Requires-Dist: pyqt5
Requires-Dist: send2trash
